image_diff/__init__.py
image_diff/__main__.py
image_diff/cli.py
image_diff-0.2.2.dist-info/LICENSE
image_diff-0.2.2.dist-info/METADATA
image_diff-0.2.2.dist-info/WHEEL
image_diff-0.2.2.dist-info/entry_points.txt
image_diff-0.2.2.dist-info/top_level.txt
image_diff-0.2.2.dist-info/RECORD
