Metadata-Version: 2.1
Name: image-diff
Version: 0.2.2
Summary: CLI tool for comparing images
Home-page: https://github.com/simonw/image-diff
Author: Simon Willison
License: Apache License, Version 2.0
Project-URL: Issues, https://github.com/simonw/image-diff/issues
Project-URL: CI, https://github.com/simonw/image-diff/actions
Project-URL: Changelog, https://github.com/simonw/image-diff/releases
Requires-Python: >=3.7
License-File: LICENSE
Requires-Dist: click
Requires-Dist: Pillow
Requires-Dist: click-default-group
Provides-Extra: test
Requires-Dist: pytest ; extra == 'test'
